Latch_behavioral.v
module Latch(
  input ns,
  input nr,
  output q,
  output nq
);

  reg q;
  reg nq;

  always @( ns or nr ) begin
    if (ns == 0 & nr == 0) begin
      q <= 1;
      nq <= 1;
    end
    else if (ns == 0 & nr == 1) begin
      q <= 1;
      nq <= 0;
    end
    else if (ns == 1 & nr == 0) begin
      q <= 0;
      nq <= 1;
    end
  end

endmodule

Latch.t.v
//==============================================================================
// Testbench for Latch
//==============================================================================

module Latch_test;

  // Local variables
  reg a, b;
  wire f, g;

  // VCD Dump
  initial begin
    $dumpfile("Latch_test.vcd");
    $dumpvars;
  end

  // Latch module
  Latch latch(
    .ns(a),
    .nr(b),
    .q(f),
    .nq(g)
  );

  // Main test
  initial begin
    a = 0;
    b = 0;

    #1
    b = 1;
    #1
    b = 0;
    #1
    a = 1;
    #1
    a = 0;
    #1
    a = 1;
    #1
    b = 1;
    #1
    a = 0;
    #1
    a = 1;
    #1
    b = 0;
    #1
    b = 1;
    #1
    a = 0;
    b = 0;
    #1

    $finish;
  end

endmodule

Latch_test.vcd
$date
	Wed Oct 06 21:05:48 2021
$end
$version
	Icarus Verilog
$end
$timescale
	1s
$end
$scope module Latch_test $end
$var wire 1 ! g $end
$var wire 1 " f $end
$var reg 1 # a $end
$var reg 1 $ b $end
$scope module latch $end
$var wire 1 ! nq $end
$var wire 1 $ nr $end
$var wire 1 # ns $end
$var wire 1 " q $end
$upscope $end
$upscope $end
$enddefinitions $end
#0
$dumpvars
0$
0#
1"
1!
$end
#1
0!
1$
#2
1!
0$
#3
0"
1#
#4
1"
0#
#5
0"
1#
#6
1$
#7
0!
1"
0#
#8
1#
#9
0"
1!
0$
#10
1$
#11
1"
0$
0#
